sdkwa_whatsapp_chatbot/__init__.py
sdkwa_whatsapp_chatbot/composer.py
sdkwa_whatsapp_chatbot/context.py
sdkwa_whatsapp_chatbot/extra.py
sdkwa_whatsapp_chatbot/markup.py
sdkwa_whatsapp_chatbot/py.typed
sdkwa_whatsapp_chatbot/session.py
sdkwa_whatsapp_chatbot/whatsapp_bot.py
sdkwa_whatsapp_chatbot/scenes/__init__.py
sdkwa_whatsapp_chatbot/scenes/base.py
sdkwa_whatsapp_chatbot/scenes/stage.py
sdkwa_whatsapp_chatbot/scenes/wizard.py
sdkwa_whatsapp_chatbot-1.0.4.dist-info/licenses/LICENSE
sdkwa_whatsapp_chatbot-1.0.4.dist-info/METADATA
sdkwa_whatsapp_chatbot-1.0.4.dist-info/WHEEL
sdkwa_whatsapp_chatbot-1.0.4.dist-info/top_level.txt
sdkwa_whatsapp_chatbot-1.0.4.dist-info/RECORD
