Metadata-Version: 2.4
Name: sdkwa-whatsapp-chatbot
Version: 1.0.4
Summary: WhatsApp Chatbot library for Python based on SDKWA API with Telegraf-like interface
Home-page: https://github.com/sdkwa/whatsapp-chatbot-python
Author: SDKWA Community
Author-email: SDKWA Community <support@sdkwa.pro>
Maintainer-email: SDKWA Community <support@sdkwa.pro>
License: MIT
Project-URL: Homepage, https://github.com/sdkwa/whatsapp-chatbot-python
Project-URL: Documentation, https://docs.sdkwa.pro
Project-URL: Repository, https://github.com/sdkwa/whatsapp-chatbot-python
Project-URL: Issues, https://github.com/sdkwa/whatsapp-chatbot-python/issues
Project-URL: Changelog, https://github.com/sdkwa/whatsapp-chatbot-python/blob/main/CHANGELOG.md
Keywords: whatsapp,chatbot,sdkwa,telegraf,messaging,api,bot,automation
Classifier: Development Status :: 4 - Beta
Classifier: Intended Audience :: Developers
Classifier: License :: OSI Approved :: MIT License
Classifier: Operating System :: OS Independent
Classifier: Programming Language :: Python :: 3
Classifier: Programming Language :: Python :: 3.8
Classifier: Programming Language :: Python :: 3.9
Classifier: Programming Language :: Python :: 3.10
Classifier: Programming Language :: Python :: 3.11
Classifier: Programming Language :: Python :: 3.12
Classifier: Topic :: Software Development :: Libraries :: Python Modules
Classifier: Topic :: Communications :: Chat
Classifier: Topic :: Internet :: WWW/HTTP :: Dynamic Content
Requires-Python: >=3.7
License-File: LICENSE
Requires-Dist: sdkwa-whatsapp-api-client>=1.0.4
Requires-Dist: requests>=2.25.0
Requires-Dist: typing-extensions>=4.0.0
Requires-Dist: pydantic>=2.0.0
Provides-Extra: dev
Requires-Dist: pytest>=7.0.0; extra == "dev"
Requires-Dist: pytest-asyncio>=0.21.0; extra == "dev"
Requires-Dist: black>=23.0.0; extra == "dev"
Requires-Dist: isort>=5.12.0; extra == "dev"
Requires-Dist: flake8>=6.0.0; extra == "dev"
Requires-Dist: mypy>=1.0.0; extra == "dev"
Requires-Dist: build>=0.10.0; extra == "dev"
Requires-Dist: twine>=4.0.0; extra == "dev"
Provides-Extra: webhook
Requires-Dist: flask>=2.0.0; extra == "webhook"
Requires-Dist: fastapi>=0.100.0; extra == "webhook"
Requires-Dist: uvicorn>=0.20.0; extra == "webhook"
Dynamic: author
Dynamic: home-page
Dynamic: license-file
Dynamic: requires-python
